CHANGELOG.md
MANIFEST.in
README.md
requirements.txt
setup.cfg
setup.py
Tonberry.egg-info/PKG-INFO
Tonberry.egg-info/SOURCES.txt
Tonberry.egg-info/dependency_links.txt
Tonberry.egg-info/requires.txt
Tonberry.egg-info/top_level.txt
tests/__init__.py
tests/test.py
tonberry/__init__.py
tonberry/app.py
tonberry/config.py
tonberry/content_types.py
tonberry/context_var_manager.py
tonberry/exceptions.py
tonberry/expose.py
tonberry/handlers.py
tonberry/header.py
tonberry/loggers.py
tonberry/models.py
tonberry/routers.py
tonberry/util.py
tonberry/websocket.py
tonberry/contexted/__init__.py
tonberry/contexted/request.py
tonberry/contexted/response.py
tonberry/contexted/session.py