Metadata-Version: 2.1
Name: Tonberry
Version: 0.2.1
Summary: ASGI compliant web microframework
Home-page: https://github.com/Ayehavgunne/Tonberry/
Author: Anthony Post
Author-email: postanthony3000@gmail.com
License: MIT License
Platform: UNKNOWN
Requires-Python: >=3.7
Provides-Extra: dev
